{"name":"build-javascript","namedChunkGroups":{"app":{"name":"app","assets":[{"name":"webpack-runtime-5c0b54d70c32fab70d1c.js","size":3873},{"name":"styles.36e1638d280316d986b1.css","size":55888},{"name":"framework-73478bf26d44c0724d9f.js","size":140342},{"name":"app-62193903ade69d11da37.js","size":69489}],"filteredAssets":0,"assetsSize":269592,"filteredAuxiliaryAssets":15,"auxiliaryAssetsSize":851770},"component---src-pages-404-js":{"name":"component---src-pages-404-js","assets":[{"name":"styles.36e1638d280316d986b1.css","size":55888},{"name":"component---src-pages-404-js-881c576b60aa4c460a07.js","size":3452}],"filteredAssets":0,"assetsSize":59340,"filteredAuxiliaryAssets":13,"auxiliaryAssetsSize":246583},"component---src-pages-index-js":{"name":"component---src-pages-index-js","assets":[{"name":"styles.36e1638d280316d986b1.css","size":55888},{"name":"019d026b-b2a531bad25d54bea711.js","size":834},{"name":"fea29d9f-fb911adc5fadf4a86d7a.js","size":923},{"name":"cb355538-3af2d7b8861ed3d2a790.js","size":1708},{"name":"component---src-pages-index-js-fa00dd5618bae1844bc3.js","size":27741}],"filteredAssets":0,"assetsSize":87094,"filteredAuxiliaryAssets":16,"auxiliaryAssetsSize":10135223},"component---src-templates-blog-post-js":{"name":"component---src-templates-blog-post-js","assets":[{"name":"styles.36e1638d280316d986b1.css","size":55888},{"name":"component---src-templates-blog-post-js-5bde3cd922b0be9ac71e.js","size":5001}],"filteredAssets":0,"assetsSize":60889,"filteredAuxiliaryAssets":13,"auxiliaryAssetsSize":251246}},"assetsByChunkName":{"app":["webpack-runtime-5c0b54d70c32fab70d1c.js","styles.36e1638d280316d986b1.css","framework-73478bf26d44c0724d9f.js","app-62193903ade69d11da37.js"],"component---src-pages-404-js":["styles.36e1638d280316d986b1.css","component---src-pages-404-js-881c576b60aa4c460a07.js"],"component---src-pages-index-js":["styles.36e1638d280316d986b1.css","019d026b-b2a531bad25d54bea711.js","fea29d9f-fb911adc5fadf4a86d7a.js","cb355538-3af2d7b8861ed3d2a790.js","component---src-pages-index-js-fa00dd5618bae1844bc3.js"],"component---src-templates-blog-post-js":["styles.36e1638d280316d986b1.css","component---src-templates-blog-post-js-5bde3cd922b0be9ac71e.js"]},"childAssetsByChunkName":{}}